arcade_calendly_api/__init__.py
arcade_calendly_api/tools/__init__.py
arcade_calendly_api/tools/request_body_schemas.py
arcade_calendly_api/wrapper_tools/CancelScheduledEvent.json
arcade_calendly_api/wrapper_tools/CreateCustomShareLink.json
arcade_calendly_api/wrapper_tools/CreateEventInvitee.json
arcade_calendly_api/wrapper_tools/CreateEventType.json
arcade_calendly_api/wrapper_tools/CreateOneOffEvent.json
arcade_calendly_api/wrapper_tools/CreateSchedulingLink.json
arcade_calendly_api/wrapper_tools/CreateWebhookSubscription.json
arcade_calendly_api/wrapper_tools/DeleteInviteeData.json
arcade_calendly_api/wrapper_tools/DeleteScheduledEventsData.json
arcade_calendly_api/wrapper_tools/DeleteWebhookSubscription.json
arcade_calendly_api/wrapper_tools/FetchEventTypeHosts.json
arcade_calendly_api/wrapper_tools/FetchOrganizationInvitation.json
arcade_calendly_api/wrapper_tools/FetchOutgoingCommunications.json
arcade_calendly_api/wrapper_tools/GetActivityLogEntries.json
arcade_calendly_api/wrapper_tools/GetCalendlyUserInfo.json
arcade_calendly_api/wrapper_tools/GetEventAvailability.json
arcade_calendly_api/wrapper_tools/GetEventDetails.json
arcade_calendly_api/wrapper_tools/GetEventInviteeInfo.json
arcade_calendly_api/wrapper_tools/GetEventInvitees.json
arcade_calendly_api/wrapper_tools/GetEventTypeAvailability.json
arcade_calendly_api/wrapper_tools/GetEventTypeInfo.json
arcade_calendly_api/wrapper_tools/GetGroupInfo.json
arcade_calendly_api/wrapper_tools/GetGroupInformation.json
arcade_calendly_api/wrapper_tools/GetGroupList.json
arcade_calendly_api/wrapper_tools/GetGroupRelationshipByUuid.json
arcade_calendly_api/wrapper_tools/GetInviteeNoShowDetails.json
arcade_calendly_api/wrapper_tools/GetOrganizationDetails.json
arcade_calendly_api/wrapper_tools/GetOrganizationInvitation.json
arcade_calendly_api/wrapper_tools/GetOrganizationInvitations.json
arcade_calendly_api/wrapper_tools/GetOrganizationMembership.json
arcade_calendly_api-3.0.0.dist-info/METADATA
arcade_calendly_api-3.0.0.dist-info/WHEEL
arcade_calendly_api-3.0.0.dist-info/entry_points.txt
arcade_calendly_api-3.0.0.dist-info/licenses/LICENSE
arcade_calendly_api-3.0.0.dist-info/RECORD
